pyhighmap.cpython-312-x86_64-linux-gnu.so
pyhighmap/__init__.py
pyhighmap/pyhighmap.cpython-312-x86_64-linux-gnu.so
pyhighmap-0.0.2.dist-info/METADATA
pyhighmap-0.0.2.dist-info/WHEEL
pyhighmap-0.0.2.dist-info/top_level.txt
pyhighmap-0.0.2.dist-info/RECORD
