Metadata-Version: 2.1
Name: pyhighmap
Version: 0.0.2
Summary: Python bindings for HighMap
Home-page: https://github.com/otto-link/pyHighMap
Author: Otto Link
Author-email: otto.link.bv@gmail.com
License: GPLv3
Classifier: Programming Language :: Python :: 3
Classifier: Programming Language :: C++
Classifier: License :: OSI Approved :: GNU General Public License v3 (GPLv3)
Classifier: Operating System :: POSIX :: Linux
Requires-Python: >=3.6
